nessaid_cli/__init__.py
nessaid_cli/cli.py
nessaid_cli/cmd.py
nessaid_cli/compiler.py
nessaid_cli/elements.py
nessaid_cli/interface.py
nessaid_cli/lex_yacc_common.py
nessaid_cli/tokens.py
nessaid_cli/utils.py
nessaid_cli/binding_parser/__init__.py
nessaid_cli/binding_parser/binding_objects.py
nessaid_cli/binding_parser/binding_text_parser.py
nessaid_cli/tokenizer/__init__.py
nessaid_cli/tokenizer/tokenizer.py
nessaid_cli_tests/__init__.py
nessaid_cli_tests/test_cli.py
nessaid_cli_tests/test_grammar.py
nessaid_cli_tests/test_tokenizer.py
nessaid_cli_tests/test_utils.py
nessaid_cli-4.1.1.dist-info/LICENCE
nessaid_cli-4.1.1.dist-info/METADATA
nessaid_cli-4.1.1.dist-info/WHEEL
nessaid_cli-4.1.1.dist-info/top_level.txt
nessaid_cli-4.1.1.dist-info/RECORD
