Metadata-Version: 2.1
Name: nessaid-cli
Version: 4.1.1
Summary: Nessaid's CLI tools
Home-page: https://github.com/saithalavi/nessaid_cli
Author: Saithalavi M
Author-email: saithalavi@gmail.com
License: MIT
Project-URL: Documentation, https://github.com/saithalavi/nessaid_cli/blob/master/README.md
Project-URL: Source, https://github.com/saithalavi/nessaid_cli
Project-URL: Tracker, https://github.com/saithalavi/nessaid_cli/issues
Keywords: cli parser cli-builder
Platform: UNKNOWN
Classifier: Development Status :: 4 - Beta
Classifier: Intended Audience :: Developers
Classifier: Topic :: Software Development :: Libraries :: Application Frameworks
Classifier: Programming Language :: Python :: 3
Classifier: License :: OSI Approved :: MIT License
Requires-Python: >=3
License-File: LICENCE
Requires-Dist: asyncio
Requires-Dist: ply
Requires-Dist: nessaid-readline (>=0.4.0)
